hypermodern_python_course/__init__.py
hypermodern_python_course/console.py
hypermodern_python_course/wikipedia.py
hypermodern_python_course-0.1.0.dist-info/entry_points.txt
hypermodern_python_course-0.1.0.dist-info/LICENSE
hypermodern_python_course-0.1.0.dist-info/WHEEL
hypermodern_python_course-0.1.0.dist-info/METADATA
hypermodern_python_course-0.1.0.dist-info/RECORD
