Metadata-Version: 2.1
Name: hypermodern-python-course
Version: 0.1.0
Summary: The hypermodern Python course
Home-page: https://github.com/Vodolazskyi/hypermodern-python-course
License: MIT
Keywords: hypermoderncourse
Author: Oleksandr Vodolazskyi
Author-email: oleksandr.vodolazskyi@gmail.com
Requires-Python: >=3.8,<4.0
Classifier: License :: OSI Approved :: MIT License
Classifier: Programming Language :: Python :: 3
Classifier: Programming Language :: Python :: 3.8
Classifier: Programming Language :: Python :: 3.9
Requires-Dist: click (>=7.1.2,<8.0.0)
Requires-Dist: desert (>=2020.11.18,<2021.0.0)
Requires-Dist: marshmallow (>=3.10.0,<4.0.0)
Requires-Dist: requests (>=2.25.1,<3.0.0)
Project-URL: Repository, https://github.com/Vodolazskyi/hypermodern-python-course
